discord_music_rpc/__init__.py
discord_music_rpc/__main__.py
discord_music_rpc/config.py
discord_music_rpc/discord_rpc.py
discord_music_rpc/main.py
discord_music_rpc/tray.py
discord_music_rpc/utils.py
discord_music_rpc/resources/cd.png
discord_music_rpc/sources/__init__.py
discord_music_rpc/sources/lastfm.py
discord_music_rpc/sources/plex.py
discord_music_rpc/sources/soundcloud.py
discord_music_rpc/sources/sources.py
discord_music_rpc/sources/spotify.py
discord_music_rpc-0.1.2.dist-info/METADATA
discord_music_rpc-0.1.2.dist-info/WHEEL
discord_music_rpc-0.1.2.dist-info/entry_points.txt
discord_music_rpc-0.1.2.dist-info/RECORD
