Metadata-Version: 2.3
Name: discord-music-rpc
Version: 0.1.2
Summary: Add your description here
Project-URL: Homepage, https://github.com/f0e/discord-music-rpc
Requires-Python: >=3.12
Requires-Dist: pillow>=11.0.0
Requires-Dist: plexapi>=4.16.0
Requires-Dist: pydantic>=2.10.3
Requires-Dist: pypresence
Requires-Dist: pystray>=0.19.5
Requires-Dist: pyyaml>=6.0.2
Requires-Dist: requests>=2.32.3
Requires-Dist: soundcloud-v2>=1.6.0
Requires-Dist: spotipy>=2.24.0
